[
    {
        "name": "Danilo u lavovskoj jami",
        "id": "rnu4sMTyVJQ",
        "url": "https://www.youtube.com/watch?v=rnu4sMTyVJQ"
    },
    {
        "name": "Rođenje Isusa Hrista",
        "id": "aNIRqm8Ulrs",
        "url": "https://www.youtube.com/watch?v=aNIRqm8Ulrs"
    },
    {
        "name": "Vaskrsenje Isusa Hrista",
        "id": "ZuCHQeper_o",
        "url": "https://www.youtube.com/watch?v=ZuCHQeper_o"
    },
    {
        "name": "Prorok Jelisije",
        "id": "cfj1Nukcr_g",
        "url": "https://www.youtube.com/watch?v=cfj1Nukcr_g"
    },
    {
        "name": "Prorok Samuilo",
        "id": "TPe9OafokfI",
        "url": "https://www.youtube.com/watch?v=TPe9OafokfI"
    },
    {
        "name": "Prorok Danilo",
        "id": "0XdkPbJ0yJU",
        "url": "https://www.youtube.com/watch?v=0XdkPbJ0yJU"
    },
    {
        "name": "Kralj je rođen",
        "id": "zIv_aHnVq3Q",
        "url": "https://www.youtube.com/watch?v=zIv_aHnVq3Q"
    },
    {
        "name": "Jovan Krstitelj",
        "id": "MAIVzaAbXn8",
        "url": "https://www.youtube.com/watch?v=MAIVzaAbXn8"
    },
    {
        "name": "Blago na nebu",
        "id": "mjUFsl_aDfU",
        "url": "https://www.youtube.com/watch?v=mjUFsl_aDfU"
    },
    {
        "name": "Izgubljeno je nađeno",
        "id": "ZXVEFxudNyQ",
        "url": "https://www.youtube.com/watch?v=ZXVEFxudNyQ"
    },
    {
        "name": "Verujem, Gospode!",
        "id": "qriXZn9ZgMg",
        "url": "https://www.youtube.com/watch?v=qriXZn9ZgMg"
    },
    {
        "name": "Gospodnja molitva",
        "id": "XxN3MGjSIMY",
        "url": "https://www.youtube.com/watch?v=XxN3MGjSIMY"
    },
    {
        "name": "Izgubljeni sin",
        "id": "u34A-Y9xPW4",
        "url": "https://www.youtube.com/watch?v=u34A-Y9xPW4"
    },
    {
        "name": "Oprosti nam naše dugove",
        "id": "J6SvQq8pI8s",
        "url": "https://www.youtube.com/watch?v=J6SvQq8pI8s"
    },
    {
        "name": "Isusova čuda",
        "id": "lkL-cn9f-tk",
        "url": "https://www.youtube.com/watch?v=lkL-cn9f-tk"
    },
    {
        "name": "Pavle iz Tarsa",
        "id": "z7Lh3pg2bBM",
        "url": "https://www.youtube.com/watch?v=z7Lh3pg2bBM"
    },
    {
        "name": "Pavlova misija",
        "id": "CVYNTIEzg9c",
        "url": "https://youtu.be/CVYNTIEzg9c"
    },
    {
        "name": "Ne tako zlatno tele",
        "id": "-PMEdvqhfFs",
        "url": "https://youtu.be/-PMEdvqhfFs"
    }
]
